valvevmf/__init__.py
valvevmf/node.py
valvevmf/parser.py
valvevmf/property_parser.py
valvevmf/property_writer.py
valvevmf/vmf.py
valvevmf/writer.py
valvevmf-0.1.2.dist-info/LICENSE.txt
valvevmf-0.1.2.dist-info/METADATA
valvevmf-0.1.2.dist-info/WHEEL
valvevmf-0.1.2.dist-info/top_level.txt
valvevmf-0.1.2.dist-info/RECORD
