Metadata-Version: 2.1
Name: valvevmf
Version: 0.1.2
Summary: A library to parse .VMF files (level editor files for the Source engine).
Home-page: https://pysourcesdk.github.io/ValveVMF/
Author: Maxime Dupuis
Author-email: mdupuis@hotmail.ca
License: gpl-3.0
Project-URL: Documentation, https://pysourcesdk.github.io/ValveVMF/
Project-URL: Github, https://github.com/pySourceSDK/ValveVMF
Keywords: vmf,source,sourcesdk,hammer,valve
Classifier: Development Status :: 3 - Alpha
Classifier: Intended Audience :: Developers
Classifier: Topic :: Software Development :: Build Tools
Classifier: License :: OSI Approved :: GNU General Public License v3 (GPLv3)
Classifier: Programming Language :: Python :: 3.7
Classifier: Programming Language :: Python :: 3.8
Classifier: Programming Language :: Python :: 3.9
Classifier: Programming Language :: Python :: 3.10
Classifier: Operating System :: Unix
Classifier: Operating System :: MacOS :: MacOS X
Classifier: Operating System :: Microsoft :: Windows
License-File: LICENSE.txt
Requires-Dist: pyparsing
Requires-Dist: future
